{"asctime": "2025-01-17 16:22:31,008", "levelname": "INFO", "name": "C2Management", "message": "==================================================", "extra_fields": {"session_id": "c84addd6-45d6-428b-9333-068765e9c440", "timestamp_unix": 1737130951.008313}, "hostname": "ubuntu-linux-22-04-02-desktop", "username": "parallels"}
{"asctime": "2025-01-17 16:22:31,008", "levelname": "INFO", "name": "C2Management", "message": "System Information", "extra_fields": {"session_id": "c84addd6-45d6-428b-9333-068765e9c440", "timestamp_unix": 1737130951.008454}, "hostname": "ubuntu-linux-22-04-02-desktop", "username": "parallels"}
{"asctime": "2025-01-17 16:22:31,008", "levelname": "INFO", "name": "C2Management", "message": "==================================================", "extra_fields": {"session_id": "c84addd6-45d6-428b-9333-068765e9c440", "timestamp_unix": 1737130951.00853}, "hostname": "ubuntu-linux-22-04-02-desktop", "username": "parallels"}
{"asctime": "2025-01-17 16:22:31,008", "levelname": "INFO", "name": "C2Management", "message": "OS: Linux 5.15.0-76-generic", "extra_fields": {"session_id": "c84addd6-45d6-428b-9333-068765e9c440", "timestamp_unix": 1737130951.008589}, "hostname": "ubuntu-linux-22-04-02-desktop", "username": "parallels"}
{"asctime": "2025-01-17 16:22:31,008", "levelname": "INFO", "name": "C2Management", "message": "Python Version: 3.10.12", "extra_fields": {"session_id": "c84addd6-45d6-428b-9333-068765e9c440", "timestamp_unix": 1737130951.008641}, "hostname": "ubuntu-linux-22-04-02-desktop", "username": "parallels"}
{"asctime": "2025-01-17 16:22:31,008", "levelname": "INFO", "name": "C2Management", "message": "CPU Cores: 3", "extra_fields": {"session_id": "c84addd6-45d6-428b-9333-068765e9c440", "timestamp_unix": 1737130951.00872}, "hostname": "ubuntu-linux-22-04-02-desktop", "username": "parallels"}
{"asctime": "2025-01-17 16:22:31,008", "levelname": "INFO", "name": "C2Management", "message": "Memory: 3GB Total, 81.5% Used", "extra_fields": {"session_id": "c84addd6-45d6-428b-9333-068765e9c440", "timestamp_unix": 1737130951.008825}, "hostname": "ubuntu-linux-22-04-02-desktop", "username": "parallels"}
{"asctime": "2025-01-17 16:22:31,008", "levelname": "INFO", "name": "C2Management", "message": "==================================================", "extra_fields": {"session_id": "c84addd6-45d6-428b-9333-068765e9c440", "timestamp_unix": 1737130951.008878}, "hostname": "ubuntu-linux-22-04-02-desktop", "username": "parallels"}
{"asctime": "2025-01-17 16:25:48,935", "levelname": "INFO", "name": "C2Management", "message": "Server shutdown initiated by user (Ctrl+C).", "extra_fields": {"session_id": "c84addd6-45d6-428b-9333-068765e9c440", "timestamp_unix": 1737131148.93584}, "hostname": "ubuntu-linux-22-04-02-desktop", "username": "parallels"}
